markata/__about__.py
markata/__init__.py
markata/__main__.py
markata/background.py
markata/errors.py
markata/exceptions.py
markata/hookspec.py
markata/lifecycle.py
markata/standard_config.py
markata/cli/__init__.py
markata/cli/__main__.py
markata/cli/cli.py
markata/cli/didyoumean.py
markata/cli/header.py
markata/cli/plugins.py
markata/cli/runner.py
markata/cli/server.py
markata/cli/summary.py
markata/plugins/Karla-Regular.ttf
markata/plugins/__init__.py
markata/plugins/analytics.py
markata/plugins/auto_description.py
markata/plugins/auto_title.py
markata/plugins/base_cli.py
markata/plugins/config_model.py
markata/plugins/copy_assets.py
markata/plugins/covers.py
markata/plugins/create_covers.py
markata/plugins/create_models.py
markata/plugins/datetime.py
markata/plugins/default_doc_template.md
markata/plugins/default_feed_style.xsl
markata/plugins/default_log_template.html
markata/plugins/default_post_template.html
markata/plugins/default_post_template.html.jinja
markata/plugins/default_redirect_template.html
markata/plugins/default_rss_template.xml
markata/plugins/default_service_worker_template.js
markata/plugins/default_sitemap_template.xml
markata/plugins/default_xsl_template.xsl
markata/plugins/didyoumean.py
markata/plugins/docs.py
markata/plugins/feeds.py
markata/plugins/flat_slug.py
markata/plugins/generator.py
markata/plugins/glob.py
markata/plugins/heading_link.py
markata/plugins/icon_resize.py
markata/plugins/jinja_env.py
markata/plugins/jinja_md.py
markata/plugins/load.py
markata/plugins/manifest.py
markata/plugins/md_it_highlight_code.py
markata/plugins/md_it_wikilinks.py
markata/plugins/mdit_details.py
markata/plugins/post_model.py
markata/plugins/post_template.py
markata/plugins/prevnext.py
markata/plugins/prevnext_template.html
markata/plugins/publish_dev_to_source.py
markata/plugins/publish_html.py
markata/plugins/publish_source.py
markata/plugins/pyinstrument.py
markata/plugins/redirects.py
markata/plugins/render_markdown.py
markata/plugins/rss.py
markata-0.10.0.dist-info/METADATA
markata-0.10.0.dist-info/WHEEL
markata-0.10.0.dist-info/entry_points.txt
markata-0.10.0.dist-info/licenses/LICENSE
markata-0.10.0.dist-info/RECORD
