Metadata-Version: 2.4
Name: markata
Version: 0.10.0
Summary: Static site generator plugins all the way down.
Project-URL: Homepage, https://markata.dev
Project-URL: Changelog, https://markata.dev/CHANGELOG/
Project-URL: Source, https://github.com/waylonwalker/markata
Project-URL: Issues, https://github.com/waylonwalker/markata/issues
Project-URL: Documentation, https://markata.dev
Author-email: Waylon Walker <waylon@waylonwalker.com>, waylon@markata.dev
License: MIT License
License-File: LICENSE
Keywords: static-site
Classifier: Development Status :: 4 - Beta
Classifier: Environment :: Console
Classifier: Environment :: Web Environment
Classifier: Intended Audience :: Developers
Classifier: License :: OSI Approved :: MIT License
Classifier: Natural Language :: English
Classifier: Operating System :: OS Independent
Classifier: Programming Language :: Python
Classifier: Programming Language :: Python :: 3
Classifier: Programming Language :: Python :: 3 :: Only
Classifier: Programming Language :: Python :: 3.7
Classifier: Programming Language :: Python :: 3.8
Classifier: Programming Language :: Python :: 3.9
Classifier: Programming Language :: Python :: 3.10
Classifier: Programming Language :: Python :: 3.11
Classifier: Programming Language :: Python :: 3.12
Classifier: Programming Language :: Python :: 3.13
Classifier: Programming Language :: Python :: Implementation :: CPython
Classifier: Programming Language :: Python :: Implementation :: PyPy
Classifier: Topic :: Documentation
Classifier: Topic :: Software Development
Classifier: Topic :: Text Processing
Classifier: Typing :: Typed
Requires-Python: >=3.6
Requires-Dist: anyconfig
Requires-Dist: beautifulsoup4
Requires-Dist: checksumdir
Requires-Dist: commonmark
Requires-Dist: cookiecutter
Requires-Dist: copier
Requires-Dist: dateparser
Requires-Dist: deepmerge
Requires-Dist: diskcache
Requires-Dist: feedgen
Requires-Dist: jinja2
Requires-Dist: linkify-it-py
Requires-Dist: markdown-it-py[plugins]
Requires-Dist: markdown2[all]
Requires-Dist: more-itertools
Requires-Dist: pathspec
Requires-Dist: pillow
Requires-Dist: pluggy
Requires-Dist: polyfactory
Requires-Dist: pydantic-extra-types>=2.0
Requires-Dist: pydantic-settings
Requires-Dist: pydantic>=2.0
Requires-Dist: pymdown-extensions
Requires-Dist: python-frontmatter
Requires-Dist: python-slugify
Requires-Dist: pytz
Requires-Dist: rich
Requires-Dist: setuptools
Requires-Dist: toml
Requires-Dist: tomli
Requires-Dist: typer
Requires-Dist: xxhash
Provides-Extra: dev
Requires-Dist: hatch; extra == 'dev'
Requires-Dist: interrogate; extra == 'dev'
Requires-Dist: mypy; extra == 'dev'
Requires-Dist: pre-commit; extra == 'dev'
Requires-Dist: pytest; extra == 'dev'
Requires-Dist: pytest-cov; extra == 'dev'
Requires-Dist: pytest-mock; extra == 'dev'
Requires-Dist: pytest-tmp-files; extra == 'dev'
Requires-Dist: ruff; extra == 'dev'
Provides-Extra: pyinstrument
Requires-Dist: pyinstrument; extra == 'pyinstrument'
Provides-Extra: tui
Requires-Dist: textual; extra == 'tui'
Requires-Dist: trogon; extra == 'tui'
